__init__.py
email_sender.py
healthcheck.py
main.py
js_web_scraper-1.2.2.dist-info/licenses/LICENSE
scrapers/__init__.py
scrapers/cars_com.py
scrapers/diff.py
scrapers/generic.py
scrapers/text.py
util/__init__.py
util/healthcheck.py
util/logging.py
js_web_scraper-1.2.2.dist-info/METADATA
js_web_scraper-1.2.2.dist-info/WHEEL
js_web_scraper-1.2.2.dist-info/top_level.txt
js_web_scraper-1.2.2.dist-info/RECORD
