Metadata-Version: 2.4
Name: js-web-scraper
Version: 1.2.2
Summary: Customizable Web Scrapper to get alerts when criteria is met on web sites.
Author-email: jnstockley <jnstockley@users.noreply.github.com>
Project-URL: Homepage, https://github.com/jnstockley/web-scraper
Project-URL: Repository, https://github.com/jnstockley/web-scraper.git
Project-URL: Issues, https://github.com/jnstockley/web-scraper/issues
Keywords: starter,template,python
Classifier: Programming Language :: Python :: 3
Requires-Python: <4.0,>=3.13
License-File: LICENSE
Requires-Dist: beautifulsoup4==4.14.3
Requires-Dist: pandas==3.0.0
Requires-Dist: python-dotenv==1.2.1
Requires-Dist: tls-client==1.0.1
Dynamic: license-file
